{
    "type": "FeatureCollection",
    "name": "2013 Itinerary 10",
    "difficulty": "Challenging",
    "miles": "67",
    "food-pickup": "3",
    "showers": "3",
    "features": [
        {
            "type": "Feature",
            "properties": {
            	"title": "Base Camp (Tent City)",
                "description": "The base camp of Philmont Scout Ranch with three groupings of tents: trailbound; homebound; staff.",
                "marker-symbol": "a",
                "marker-color": "#34495E",
                "elevation": "6691",
                "water-source": "plumbing",
                "facilities": "none",
                "location-type": "base camp",
                "program": "campfire"
            },
            "geometry": {
                "type": "Point",
                "coordinates": [
                    -104.95904,
                    36.45168
                ]
            }
        },
        {
            "type": "Feature",
            "properties": {
            	"title": "Bent Camp",
                "description": "Bent is a starting camp northwest of Ponil.",
                "elevation": "7320",
                "marker-symbol": "1",
                "marker-color": "#2980B9",
                "water-source": "stream",
                "facilities": "none",
                "location-type": "trail camp",
                "program": "none"
            },
            "geometry": {
                "type": "Point",
                "coordinates": [
                    -105.06604,
                    36.63567
                ]
            }
        },
        {
            "type": "Feature",
            "properties": {
                "description": "Dan Beard",
                "elevation": null,
                "marker-symbol": "2",
                "marker-color": "#2980B9",
                "symbol": "Waypoint"
            },
            "geometry": {
                "type": "Point",
                "coordinates": [
                    -105.08892,
                    36.67821
                ]
            }
        },
        {
            "type": "Feature",
            "properties": {
                "description": "Seally Canyon Camp",
                "elevation": null,
                "marker-symbol": "3",
                "marker-color": "#2980B9",
                "symbol": "Waypoint"
            },
            "geometry": {
                "type": "Point",
                "coordinates": [
                    -105.10081,
                    36.75258
                ]
            }
        },
        {
            "type": "Feature",
            "properties": {
                "description": "Whiteman Vega",
                "elevation": null,
                "marker-symbol": "4",
                "marker-color": "#2980B9",
                "symbol": "Waypoint"
            },
            "geometry": {
                "type": "Point",
                "coordinates": [
                    -105.102,
                    36.79377
                ]
            }
        },
        {
	        "type": "Feature",
	        "properties": {
		        "description": "Iris Park",
		        "elevation" : 8530,
		        "marker-symbol": "5",
		        "marker-color": "#2980B9",
		        "symbol": "waypoint"
	        },
	        "geometry": {
		        "type": "Point",
		        "coordinates": [
		        	-105.155645,
		        	36.727193
		        ]
	        }
        }
	]
}
